hypercoast/__init__.py
hypercoast/aviris.py
hypercoast/chla.py
hypercoast/common.py
hypercoast/desis.py
hypercoast/emit.py
hypercoast/enmap.py
hypercoast/hypercoast.py
hypercoast/neon.py
hypercoast/pace.py
hypercoast/prisma.py
hypercoast/tanager.py
hypercoast/ui.py
hypercoast/wyvern.py
hypercoast/emit_utils/MoE_VAE.py
hypercoast/emit_utils/__init__.py
hypercoast/emit_utils/data_loading.py
hypercoast/emit_utils/model_inference.py
hypercoast/emit_utils/plot_and_save.py
hypercoast/emit_utils/preprocess.py
hypercoast/moe_vae/__init__.py
hypercoast/moe_vae/data_loading.py
hypercoast/moe_vae/model.py
hypercoast/moe_vae/model_inference.py
hypercoast/moe_vae/plot_and_save.py
hypercoast/moe_vae/preprocess.py
hypercoast-0.19.0.dist-info/licenses/LICENSE
hypercoast-0.19.0.dist-info/METADATA
hypercoast-0.19.0.dist-info/WHEEL
hypercoast-0.19.0.dist-info/entry_points.txt
hypercoast-0.19.0.dist-info/top_level.txt
hypercoast-0.19.0.dist-info/RECORD
