Metadata-Version: 2.4
Name: HyperCoast
Version: 0.19.0
Summary: A Python package for processing hyperspectral data in coastal regions
Author-email: Qiusheng Wu <giswqs@gmail.com>
License: MIT License
Project-URL: Homepage, https://github.com/opengeos/HyperCoast
Keywords: HyperCoast
Classifier: Intended Audience :: Developers
Classifier: License :: OSI Approved :: MIT License
Classifier: Natural Language :: English
Classifier: Programming Language :: Python :: 3.9
Classifier: Programming Language :: Python :: 3.10
Classifier: Programming Language :: Python :: 3.11
Classifier: Programming Language :: Python :: 3.12
Requires-Python: >=3.9
License-File: LICENSE
Requires-Dist: dask
Requires-Dist: earthaccess
Requires-Dist: geopandas
Requires-Dist: h5netcdf
Requires-Dist: h5py
Requires-Dist: hvplot
Requires-Dist: leafmap>=0.38.0
Requires-Dist: localtileserver
Requires-Dist: mapclassify
Requires-Dist: netcdf4
Requires-Dist: numpy
Requires-Dist: openpyxl
Requires-Dist: psutil
Requires-Dist: rioxarray
Requires-Dist: s3fs
Requires-Dist: scikit-learn
Requires-Dist: scipy
Requires-Dist: seaborn
Requires-Dist: xarray
Provides-Extra: all
Requires-Dist: HyperCoast[extra]; extra == "all"
Requires-Dist: HyperCoast[torch]; extra == "all"
Provides-Extra: extra
Requires-Dist: cartopy; extra == "extra"
Requires-Dist: fiona; extra == "extra"
Requires-Dist: geopandas; extra == "extra"
Requires-Dist: openpyxl; extra == "extra"
Requires-Dist: pyvista[jupyter]; extra == "extra"
Requires-Dist: scikit-learn; extra == "extra"
Provides-Extra: torch
Requires-Dist: torch; extra == "torch"
Requires-Dist: seaborn; extra == "torch"
Requires-Dist: pytorch-lightning; extra == "torch"
Dynamic: license-file
